little_a2s/__init__.py
little_a2s/client/__init__.py
little_a2s/client/async_.py
little_a2s/client/constants.py
little_a2s/client/sync.py
little_a2s/client/types.py
little_a2s/enums.py
little_a2s/events.py
little_a2s/headers.py
little_a2s/packets.py
little_a2s/protocol.py
little_a2s/reader.py
little_a2s/rules/__init__.py
little_a2s/rules/arma3.py
little_a2s-0.5.2.dist-info/licenses/LICENSE
little_a2s-0.5.2.dist-info/WHEEL
little_a2s-0.5.2.dist-info/METADATA
little_a2s-0.5.2.dist-info/RECORD
