Metadata-Version: 2.4
Name: little-a2s
Version: 0.5.2
Summary: A sync + async + sans-I/O library for the Valve Source Query (A2S) protocol.
Author: thegamecracks
License-Expression: MIT
License-File: LICENSE
Classifier: Development Status :: 3 - Alpha
Classifier: Intended Audience :: Developers
Classifier: Operating System :: OS Independent
Classifier: Programming Language :: Python
Classifier: Programming Language :: Python :: 3
Classifier: Programming Language :: Python :: 3 :: Only
Classifier: Programming Language :: Python :: 3.11
Classifier: Programming Language :: Python :: 3.12
Classifier: Programming Language :: Python :: 3.13
Classifier: Programming Language :: Python :: 3.14
Classifier: Programming Language :: SQL
Classifier: Topic :: Internet
Classifier: Topic :: System :: Networking
Classifier: Typing :: Typed
Requires-Python: >=3.11
Project-URL: Documentation, https://little-a2s.rtfd.io/
Project-URL: GitHub, https://github.com/thegamecracks/little-a2s
Project-URL: Homepage, https://little-a2s.rtfd.io/
Project-URL: Issues, https://github.com/thegamecracks/little-a2s/issues
